{"trial_id": "021", "hyperparameters": {"space": [{"class_name": "Int", "config": {"name": "num_layers", "default": null, "conditions": [], "min_value": 2, "max_value": 5, "step": 1, "sampling": "linear"}}, {"class_name": "Choice", "config": {"name": "dense_activation", "default": "relu", "conditions": [], "values": ["relu", "leaky_relu", "elu"], "ordered": false}}, {"class_name": "Int", "config": {"name": "units_0", "default": null, "conditions": [], "min_value": 2, "max_value": 16, "step": 2, "sampling": "linear"}}, {"class_name": "Choice", "config": {"name": "dropout_rate", "default": 0.3, "conditions": [], "values": [0.3, 0.4, 0.5], "ordered": true}}, {"class_name": "Int", "config": {"name": "units_1", "default": null, "conditions": [], "min_value": 2, "max_value": 16, "step": 2, "sampling": "linear"}}, {"class_name": "Float", "config": {"name": "learning_rate", "default": 0.001, "conditions": [], "min_value": 5e-05, "max_value": 0.005, "step": null, "sampling": "log"}}, {"class_name": "Int", "config": {"name": "units_2", "default": null, "conditions": [], "min_value": 2, "max_value": 16, "step": 2, "sampling": "linear"}}, {"class_name": "Int", "config": {"name": "units_3", "default": null, "conditions": [], "min_value": 2, "max_value": 16, "step": 2, "sampling": "linear"}}, {"class_name": "Int", "config": {"name": "units_4", "default": null, "conditions": [], "min_value": 2, "max_value": 16, "step": 2, "sampling": "linear"}}], "values": {"num_layers": 5, "dense_activation": "elu", "units_0": 4, "dropout_rate": 0.5, "units_1": 6, "learning_rate": 0.0008923312866770331, "units_2": 16, "units_3": 8, "units_4": 14}}, "metrics": {"metrics": {"loss": {"direction": "min", "observations": [{"value": [1.120930790901184], "step": 4}]}, "categorical_accuracy": {"direction": "max", "observations": [{"value": [0.4336884617805481], "step": 4}]}, "val_loss": {"direction": "min", "observations": [{"value": [1.0475192070007324], "step": 4}]}, "val_categorical_accuracy": {"direction": "max", "observations": [{"value": [0.6119225025177002], "step": 4}]}}}, "score": 0.6119225025177002, "best_step": 4, "status": "COMPLETED", "message": null}