{"trial_id": "075", "hyperparameters": {"space": [{"class_name": "Float", "config": {"name": "l1", "default": 0, "conditions": [], "min_value": 1e-06, "max_value": 0.1, "step": null, "sampling": "log"}}, {"class_name": "Float", "config": {"name": "l2", "default": 0, "conditions": [], "min_value": 1e-06, "max_value": 0.1, "step": null, "sampling": "log"}}, {"class_name": "Choice", "config": {"name": "dense_activation", "default": "relu", "conditions": [], "values": ["relu", "leaky_relu", "elu"], "ordered": false}}, {"class_name": "Int", "config": {"name": "num_layers", "default": null, "conditions": [], "min_value": 2, "max_value": 5, "step": 1, "sampling": "linear"}}, {"class_name": "Int", "config": {"name": "units_0", "default": null, "conditions": [], "min_value": 2, "max_value": 16, "step": 2, "sampling": "linear"}}, {"class_name": "Choice", "config": {"name": "dropout_rate", "default": 0.3, "conditions": [], "values": [0.3, 0.4, 0.5], "ordered": true}}, {"class_name": "Int", "config": {"name": "units_1", "default": null, "conditions": [], "min_value": 2, "max_value": 16, "step": 2, "sampling": "linear"}}, {"class_name": "Float", "config": {"name": "learning_rate", "default": 0.001, "conditions": [], "min_value": 5e-05, "max_value": 0.005, "step": null, "sampling": "log"}}, {"class_name": "Int", "config": {"name": "units_2", "default": null, "conditions": [], "min_value": 2, "max_value": 16, "step": 2, "sampling": "linear"}}, {"class_name": "Int", "config": {"name": "units_3", "default": null, "conditions": [], "min_value": 2, "max_value": 16, "step": 2, "sampling": "linear"}}, {"class_name": "Int", "config": {"name": "units_4", "default": null, "conditions": [], "min_value": 2, "max_value": 16, "step": 2, "sampling": "linear"}}], "values": {"l1": 0.0010609008217589207, "l2": 6.739256029546032e-05, "dense_activation": "elu", "num_layers": 5, "units_0": 4, "dropout_rate": 0.4, "units_1": 10, "learning_rate": 5.2308714968092523e-05, "units_2": 4, "units_3": 16, "units_4": 12}}, "metrics": {"metrics": {"loss": {"direction": "min", "observations": [{"value": [1.191855549812317], "step": 30}]}, "categorical_accuracy": {"direction": "max", "observations": [{"value": [0.4492059648036957], "step": 30}]}, "val_loss": {"direction": "min", "observations": [{"value": [1.0815212726593018], "step": 30}]}, "val_categorical_accuracy": {"direction": "max", "observations": [{"value": [0.5786474347114563], "step": 30}]}}}, "score": 0.5786474347114563, "best_step": 30, "status": "COMPLETED", "message": null}